PUI/__init__.py
PUI/common.py
PUI/decorator.py
PUI/dom.py
PUI/interfaces.py
PUI/node.py
PUI/state.py
PUI/timeline.py
PUI/utils.py
PUI/view.py
PUI/PySide6/__init__.py
PUI/PySide6/application.py
PUI/PySide6/base.py
PUI/PySide6/button.py
PUI/PySide6/canvas.py
PUI/PySide6/checkbox.py
PUI/PySide6/combobox.py
PUI/PySide6/dialog.py
PUI/PySide6/divider.py
PUI/PySide6/image.py
PUI/PySide6/label.py
PUI/PySide6/layout.py
PUI/PySide6/matplotlib.py
PUI/PySide6/mdi.py
PUI/PySide6/menu.py
PUI/PySide6/modal.py
PUI/PySide6/progressbar.py
PUI/PySide6/radiobutton.py
PUI/PySide6/scroll.py
PUI/PySide6/splitter.py
PUI/PySide6/tab.py
PUI/PySide6/table.py
PUI/PySide6/text.py
PUI/PySide6/textfield.py
PUI/PySide6/toolbar.py
PUI/PySide6/tree.py
PUI/PySide6/window.py
PUI/flet/__init__.py
PUI/flet/application.py
PUI/flet/base.py
PUI/flet/button.py
PUI/flet/canvas.py
PUI/flet/checkbox.py
PUI/flet/divider.py
PUI/flet/label.py
PUI/flet/layout.py
PUI/flet/progressbar.py
PUI/flet/radiobutton.py
PUI/flet/scroll.py
PUI/flet/tab.py
PUI/flet/text.py
PUI/flet/textfield.py
PUI/flet/window.py
PUI/textual/__init__.py
PUI/textual/application.py
PUI/textual/base.py
PUI/textual/button.py
PUI/textual/checkbox.py
PUI/textual/label.py
PUI/textual/layout.py
PUI/textual/progressbar.py
PUI/textual/radiobutton.py
PUI/textual/scroll.py
PUI/textual/tab.py
PUI/textual/text.py
PUI/textual/textfield.py
PUI/textual/window.py
PUI/tkinter/__init__.py
PUI/tkinter/application.py
PUI/tkinter/base.py
PUI/tkinter/button.py
PUI/tkinter/canvas.py
PUI/tkinter/checkbox.py
PUI/tkinter/label.py
PUI/tkinter/layout.py
PUI/tkinter/progressbar.py
PUI/tkinter/radiobutton.py
PUI/tkinter/scroll.py
PUI/tkinter/tab.py
PUI/tkinter/text.py
PUI/tkinter/textfield.py
PUI/tkinter/window.py
PUI/wx/__init__.py
PUI/wx/application.py
PUI/wx/base.py
PUI/wx/button.py
PUI/wx/canvas.py
PUI/wx/checkbox.py
PUI/wx/combobox.py
PUI/wx/dialog.py
PUI/wx/divider.py
PUI/wx/label.py
PUI/wx/layout.py
PUI/wx/progressbar.py
PUI/wx/radiobutton.py
PUI/wx/scroll.py
qpuiq-0.27.dist-info/LICENSE.txt
qpuiq-0.27.dist-info/METADATA
qpuiq-0.27.dist-info/WHEEL
qpuiq-0.27.dist-info/top_level.txt
qpuiq-0.27.dist-info/RECORD
