Metadata-Version: 2.1
Name: qpuiq
Version: 0.27
Summary: "PUI" Python Declarative UI Framework
Home-page: https://github.com/buganini/PUI
Author: Buganini Chiu
Author-email: buganini@b612.tw
License-File: LICENSE.txt
